Scmepy/Scmepy.py
Scmepy/__init__.py
Scmepy-0.0.1.dist-info/LICENSE
Scmepy-0.0.1.dist-info/METADATA
Scmepy-0.0.1.dist-info/WHEEL
Scmepy-0.0.1.dist-info/top_level.txt
Scmepy-0.0.1.dist-info/RECORD
