Metadata-Version: 2.1
Name: Scmepy
Version: 0.0.1
Summary: Um conversor de varias unidades de medida
Home-page: https://github.com/Ericksulino/SCMEPY.git
Author: Ericksulino Moura, José Miqueias
Author-email: ericksulino@gmail.com
License: UNKNOWN
Project-URL: Bug Tracker, https://github.com/pypa/sampleproject/issues
Platform: UNKNOWN
Classifier: Programming Language :: Python :: 3
Classifier: License :: OSI Approved :: MIT License
Classifier: Operating System :: OS Independent
Requires-Python: >=3.6
License-File: LICENSE
